deepctools/DeePCtools.py
deepctools/Modeltools.py
deepctools/__init__.py
deepctools/util.py
deepctools-1.1.5.dist-info/METADATA
deepctools-1.1.5.dist-info/WHEEL
deepctools-1.1.5.dist-info/licenses/LICENSE
deepctools-1.1.5.dist-info/RECORD
