Metadata-Version: 2.3
Name: deepctools
Version: 1.1.5
Summary: A wrapped package for Data-enabled predictive control (DeePC) implementation. Including DeePC and Robust DeePC design with multiple objective functions.
Project-URL: Homepage, https://github.com/QiYuan-Zhang/DeePCtools
Project-URL: Issues, https://github.com/QiYuan-Zhang/DeePCtools/issues
Project-URL: Introduction, https://qiyuan-zhang.github.io/my-toolbox/2024/04/15/Developed-deepctools.html
Author-email: Xuewen Zhang <xuewen.zhang741@outlook.com>
Maintainer-email: Xuewen Zhang <xuewen.zhang741@outlook.com>
License:                                 Apache License
Keywords: Data-driven control,DeePC,MPC,RDeePC,Robust DeePC,data-driven MPC,data-enabled predictive control,model-free-control
Classifier: Development Status :: 4 - Beta
Classifier: Intended Audience :: Developers
Classifier: License :: OSI Approved :: Apache Software License
Classifier: Programming Language :: Python :: 3
Classifier: Programming Language :: Python :: 3.6
Classifier: Programming Language :: Python :: 3.7
Classifier: Programming Language :: Python :: 3.8
Classifier: Programming Language :: Python :: 3.9
Classifier: Topic :: Software Development :: Build Tools
Requires-Python: >=3.7
Requires-Dist: casadi>3.0.0
Requires-Dist: numpy
